NuGigSkillNER/__init__.py
NuGigSkillNER/cleaner.py
NuGigSkillNER/general_params.py
NuGigSkillNER/matcher_class.py
NuGigSkillNER/skill_extractor_class.py
NuGigSkillNER/text_class.py
NuGigSkillNER/utils.py
NuGigSkillNER/network/__init__.py
NuGigSkillNER/network/remote_db.py
skillNer/__init__.py
skillNer/cleaner.py
skillNer/general_params.py
skillNer/matcher_class.py
skillNer/skill_extractor_class.py
skillNer/text_class.py
skillNer/utils.py
skillNer/network/__init__.py
skillNer/network/remote_db.py
skillNer/visualizer/__init__.py
skillNer/visualizer/html_elements.py
skillNer/visualizer/phrase_class.py
skills_processor/__init__.py
skills_processor/create_new_skill.py
skills_processor/create_surf_db.py
skills_processor/create_token_dist.py
skills_processor/fetch_raw_data.py
NUGigSkillNER-2.0.4.dist-info/LICENSE
NUGigSkillNER-2.0.4.dist-info/METADATA
NUGigSkillNER-2.0.4.dist-info/WHEEL
NUGigSkillNER-2.0.4.dist-info/top_level.txt
NUGigSkillNER-2.0.4.dist-info/RECORD
