Metadata-Version: 2.1
Name: NUGigSkillNER
Version: 2.0.4
Summary: An NLP module to automatically Extract skills and certifications from unstructured job postings, texts, and applicant's resumes
Home-page: https://github.com/emandel2630/NUGigSkillNER
Author: Ethan Mandel
Author-email: emandel2630@gmail.com
Keywords: skillNer,python,NLP,NER,skills-extraction,job-description
Classifier: Programming Language :: Python :: 3
Classifier: License :: OSI Approved :: MIT License
Classifier: Operating System :: OS Independent
License-File: LICENSE
Requires-Dist: numpy
Requires-Dist: pandas
Requires-Dist: nltk
Requires-Dist: spacy
Requires-Dist: jellyfish
Requires-Dist: scipy
